{"DemoMsg/Demo164_0:Demo164_0_Text002": {"contents": [{"text": "You have been asleep\nfor the past 100 years."}]}, "DemoMsg/Demo164_0:Demo164_0_Text003": {"contents": [{"control": {"kind": "text_size", "percent": 80}}, {"text": "Remember... "}, {"control": {"kind": "text_size", "percent": 100}}]}, "DemoMsg/Demo164_0:Demo164_0_Text004": {"contents": [{"text": "Try... Try to remember..."}]}, "DemoMsg/Demo164_0:Demo164_0_Text005": {"contents": [{"text": "The beast..."}, {"control": {"kind": "raw", "zero": {"four": {"field_1": 0}}}}, {"text": "When the beast regains its true power,\nthis world will face its end."}]}, "DemoMsg/Demo164_0:Demo164_0_Text006": {"contents": [{"text": "Now then..."}]}, "DemoMsg/Demo164_0:Demo164_0_Text007": {"contents": [{"text": "You must hurry, Link."}]}, "DemoMsg/Demo164_0:Demo164_0_Text008": {"contents": [{"text": "Before it's too late..."}]}, "DemoMsg/Demo164_0:Demo164_0_Text009": {"contents": [{"text": "...urgh!"}]}, "DemoMsg/Demo164_0:Demo164_0_Text010": {"contents": [{"text": "Whoop..."}]}}