[{"type": "node", "id": -1000, "data": {"name": "Talk"}, "node_type": "entry"}, {"type": "edge", "source": -1000, "target": 0, "data": {}}, {"type": "node", "id": 0, "data": {"res_flowchart_name": "InitTalk", "entry_point_name": "InitTalk", "name": "Event1", "params": {"Arg_Turn": 0, "Arg_Greeting": "FollowAISchedule"}}, "node_type": "sub_flow"}, {"type": "edge", "source": 0, "target": 66, "data": {}}, {"type": "node", "id": 66, "data": {"actor": "Npc_oasis023", "query": "IsOnInstEventFlag", "name": "Event116", "params": null}, "node_type": "switch"}, {"type": "edge", "source": 66, "target": 56, "data": {"value": 1}}, {"type": "node", "id": 56, "data": {"res_flowchart_name": "", "entry_point_name": "SINJYU_CK", "name": "Event104", "params": null}, "node_type": "sub_flow"}, {"type": "edge", "source": 56, "target": 69, "data": {}}, {"type": "node", "id": 69, "data": {"actor": "EventSystemActor", "query": "CheckFlag", "name": "Event120", "params": {"FlagName": "Electric_Relic_GetBack"}}, "node_type": "switch"}, {"type": "edge", "source": 69, "target": 70, "data": {"value": 1}}, {"type": "node", "id": 70, "data": {"actor": "RemainsElectric[Thunder_Relic02]", "action": "Demo_Join", "name": "Event121", "params": {"IsWaitFinish": false}}, "node_type": "action"}, {"type": "edge", "source": 70, "target": 33, "data": {}}, {"type": "node", "id": 33, "data": {"actor": "EventSystemActor", "query": "CheckEquipArmorSeriesType", "name": "Event77", "params": {"CheckHead": true, "CheckLower": true, "CheckType": "GerudoCloth", "CheckUpper": true}}, "node_type": "switch"}, {"type": "edge", "source": 33, "target": 2, "data": {"value": 1}}, {"type": "node", "id": 2, "data": {"actor": "EventSystemActor", "query": "CheckFlag", "name": "Event17", "params": {"FlagName": "IsPlayed_Demo125_0"}}, "node_type": "switch"}, {"type": "edge", "source": 2, "target": 5, "data": {"value": 1}}, {"type": "node", "id": 5, "data": {"actor": "Npc_oasis023", "action": "Demo_Talk", "name": "Event20", "params": {"IsWaitFinish": true, "IsCloseMessageDialog": false, "ASName": "", "IsBecomingSpeaker": true, "MessageId": "EventFlowMsg/Npc_oasis023:Npc_oasis023_006", "IsOverWriteLabelActorName": false}}, "node_type": "action"}, {"type": "edge", "source": 2, "target": 3, "data": {"value": 0}}, {"type": "node", "id": 3, "data": {"actor": "Npc_oasis023", "action": "Demo_Talk", "name": "Event18", "params": {"IsWaitFinish": true, "ASName": "", "IsBecomingSpeaker": true, "MessageId": "EventFlowMsg/Npc_oasis023:Npc_oasis023_004", "IsOverWriteLabelActorName": false, "IsCloseMessageDialog": true}}, "node_type": "action"}, {"type": "edge", "source": 3, "target": 19, "data": {}}, {"type": "node", "id": 19, "data": {"actor": "EventSystemActor", "query": "GeneralChoice3", "name": "Event44", "params": null}, "node_type": "switch"}, {"type": "edge", "source": 19, "target": 25, "data": {"value": 0}}, {"type": "node", "id": 25, "data": {"actor": "GameRomCamera", "action": "Demo_SavePoint1", "name": "Event61", "params": {"IsWaitFinish": true}}, "node_type": "action"}, {"type": "edge", "source": 25, "target": 71, "data": {}}, {"type": "node", "id": 71, "data": {"actor": "EventSystemActor", "query": "CheckFlag", "name": "Event122", "params": {"FlagName": "Electric_Relic_GetBack"}}, "node_type": "switch"}, {"type": "edge", "source": 71, "target": 72, "data": {"value": 1}}, {"type": "node", "id": 72, "data": {"actor": "Npc_oasis023", "action": "Demo_TurnAndLookToObject", "name": "Event123", "params": {"ObjectId": 1, "IsValid": true, "FaceId": 2, "ActorName": "RemainsElectric", "IsWaitFinish": true, "IsConfront": true, "PosOffset": [0.0, 0.0, 0.0], "TurnPosition": [0.0, 0.0, 0.0], "TurnDirection": 0.0, "UniqueName": "Thunder_Relic02"}}, "node_type": "action"}, {"type": "edge", "source": 72, "target": 73, "data": {}}, {"type": "node", "id": 73, "data": {"actor": "GameROMPlayer", "action": "Demo_PlayerTurnAndLookToObject", "name": "Event124", "params": {"IsUseSlowTurn": false, "IsValid": true, "FaceId": 2, "ActorName": "RemainsElectric", "IsWaitFinish": true, "ObjectId": 0, "PosOffset": [0.0, 0.0, 0.0], "TurnPosition": [0.0, 0.0, 0.0], "TurnDirection": 0.0, "UniqueName": "Thunder_Relic02", "IsTurnToLookAtPos": false}}, "node_type": "action"}, {"type": "edge", "source": 73, "target": 74, "data": {}}, {"type": "node", "id": 74, "data": {"actor": "EventSystemActor", "action": "Demo_WaitFrame", "name": "Event128", "params": {"IsWaitFinish": true, "Frame": 5}}, "node_type": "action"}, {"type": "edge", "source": 74, "target": 75, "data": {}}, {"type": "node", "id": 75, "data": {"actor": "GameRomCamera", "action": "Demo_MovePosFlow", "name": "Event130", "params": {"ActorName1": "RemainsElectric", "UniqueName2": "", "IsWaitFinish": true, "FovyAppendMode": 1, "UniqueName1": "Thunder_Relic01", "ActorName2": "Npc_oasis023", "PosAppendMode": 3, "MotionMode": 1, "TargetActor2": 3, "Cushion": 0.0, "LatShiftRange": 30.0, "LngShiftRange": 30.0, "ActorIgnoringCollision": -1, "Pattern1PosX": 0.0, "Pattern1PosZ": 0.0, "ReviseModeEnd": 0, "Pattern1PosY": 5.0, "Count": 30.0, "StartCalcOnly": true, "TargetActor1": -1, "AtAppendMode": 1, "Accept1FrameDelay": false, "CollisionInterpolateSkip": true, "Pattern1AtX": -3545.14111328125, "Pattern1AtY": 164.09800720214844, "Pattern1AtZ": 3131.18896484375, "Pattern1Fovy": 20.0, "GameDataVec3fCameraPos": "", "GameDataVec3fCameraAt": ""}}, "node_type": "action"}, {"type": "edge", "source": 75, "target": 29, "data": {}}, {"type": "node", "id": 29, "data": {"actor": "GameRomCamera", "action": "Demo_PlayerHideOff", "name": "Event66", "params": {"IsWaitFinish": true}}, "node_type": "action"}, {"type": "edge", "source": 29, "target": 28, "data": {}}, {"type": "node", "id": 28, "data": {"actor": "EventSystemActor", "action": "Demo_WaitFrame", "name": "Event65", "params": {"IsWaitFinish": true, "Frame": 20}}, "node_type": "action"}, {"type": "edge", "source": 28, "target": 68, "data": {}}, {"type": "node", "id": 68, "data": {"actor": "Npc_oasis023", "action": "Demo_Talk", "name": "Event119", "params": {"IsWaitFinish": true, "ASName": "", "IsBecomingSpeaker": true, "IsOverWriteLabelActorName": false, "IsCloseMessageDialog": true, "MessageId": "EventFlowMsg/Npc_oasis023:Npc_oasis023_007"}}, "node_type": "action"}, {"type": "edge", "source": 68, "target": 27, "data": {}}, {"type": "node", "id": 27, "data": {"actor": "EventSystemActor", "action": "Demo_WaitFrame", "name": "Event64", "params": {"Frame": 30, "IsWaitFinish": true}}, "node_type": "action"}, {"type": "edge", "source": 27, "target": 26, "data": {}}, {"type": "node", "id": 26, "data": {"actor": "GameRomCamera", "action": "Demo_ReturnSavePoint_1", "name": "Event62", "params": {"IsWaitFinish": true, "CollisionInterpolateSkip": true, "ReviseMode": 1, "Count": 0.0}}, "node_type": "action"}, {"type": "edge", "source": 26, "target": 39, "data": {}}, {"type": "node", "id": 39, "data": {"actor": "Npc_oasis023", "action": "Demo_TurnAndLookToObject", "name": "Event84", "params": {"IsValid": false, "FaceId": 2, "ObjectId": 0, "IsWaitFinish": true, "IsConfront": true, "ActorName": "", "UniqueName": "", "PosOffset": [0.0, 0.0, 0.0], "TurnPosition": [0.0, 0.0, 0.0], "TurnDirection": 0.0}}, "node_type": "action"}, {"type": "edge", "source": 39, "target": 40, "data": {}}, {"type": "node", "id": 40, "data": {"actor": "GameROMPlayer", "action": "Demo_PlayerTurnAndLookToObject", "name": "Event85", "params": {"ObjectId": 0, "IsValid": true, "FaceId": 2, "ActorName": "Npc_oasis023", "IsUseSlowTurn": false, "IsWaitFinish": true, "UniqueName": "", "PosOffset": [0.0, 0.0, 0.0], "TurnPosition": [0.0, 0.0, 0.0], "TurnDirection": 0.0, "IsTurnToLookAtPos": false}}, "node_type": "action"}, {"type": "edge", "source": 40, "target": 23, "data": {}}, {"type": "node", "id": 23, "data": {"actor": "Npc_oasis023", "action": "Demo_Talk", "name": "Event49", "params": {"IsWaitFinish": true, "ASName": "", "IsBecomingSpeaker": true, "IsOverWriteLabelActorName": false, "MessageId": "EventFlowMsg/Npc_oasis023:Npc_oasis023_012", "IsCloseMessageDialog": true}}, "node_type": "action"}, {"type": "edge", "source": 23, "target": 19, "data": {}}, {"type": "edge", "source": 71, "target": 36, "data": {"value": 0}}, {"type": "node", "id": 36, "data": {"actor": "Npc_oasis023", "action": "Demo_TurnAndLookToObject", "name": "Event80", "params": {"ObjectId": 1, "IsValid": true, "FaceId": 2, "ActorName": "RemainsElectric", "UniqueName": "Thunder_Relic01", "IsWaitFinish": true, "IsConfront": true, "PosOffset": [0.0, 0.0, 0.0], "TurnPosition": [0.0, 0.0, 0.0], "TurnDirection": 0.0}}, "node_type": "action"}, {"type": "edge", "source": 36, "target": 37, "data": {}}, {"type": "node", "id": 37, "data": {"actor": "GameROMPlayer", "action": "Demo_PlayerTurnAndLookToObject", "name": "Event82", "params": {"IsUseSlowTurn": false, "IsValid": true, "FaceId": 2, "ActorName": "RemainsElectric", "UniqueName": "Thunder_Relic01", "IsWaitFinish": true, "ObjectId": 0, "PosOffset": [0.0, 0.0, 0.0], "TurnPosition": [0.0, 0.0, 0.0], "TurnDirection": 0.0, "IsTurnToLookAtPos": false}}, "node_type": "action"}, {"type": "edge", "source": 37, "target": 38, "data": {}}, {"type": "node", "id": 38, "data": {"actor": "EventSystemActor", "action": "Demo_WaitFrame", "name": "Event83", "params": {"IsWaitFinish": true, "Frame": 5}}, "node_type": "action"}, {"type": "edge", "source": 38, "target": 31, "data": {}}, {"type": "node", "id": 31, "data": {"actor": "GameRomCamera", "action": "Demo_MovePosFlow", "name": "Event74", "params": {"ActorName1": "RemainsElectric", "UniqueName2": "", "IsWaitFinish": true, "FovyAppendMode": 1, "UniqueName1": "Thunder_Relic01", "ActorName2": "Npc_oasis023", "PosAppendMode": 3, "MotionMode": 1, "TargetActor2": 3, "Cushion": 0.0, "LatShiftRange": 30.0, "LngShiftRange": 30.0, "ActorIgnoringCollision": -1, "Pattern1PosX": 0.0, "Pattern1PosZ": 0.0, "ReviseModeEnd": 0, "Pattern1PosY": 5.0, "Count": 30.0, "StartCalcOnly": true, "TargetActor1": -1, "AtAppendMode": 1, "Pattern1AtY": 164.67630004882812, "Pattern1AtX": -3686.569091796875, "Pattern1AtZ": 3028.280029296875, "Accept1FrameDelay": false, "CollisionInterpolateSkip": true, "Pattern1Fovy": 45.0, "GameDataVec3fCameraPos": "", "GameDataVec3fCameraAt": ""}}, "node_type": "action"}, {"type": "edge", "source": 31, "target": 29, "data": {}}, {"type": "edge", "source": 19, "target": 30, "data": {"value": 1}}, {"type": "node", "id": 30, "data": {"actor": "GameRomCamera", "action": "Demo_SavePoint1", "name": "Event69", "params": {"IsWaitFinish": true}}, "node_type": "action"}, {"type": "edge", "source": 30, "target": 41, "data": {}}, {"type": "node", "id": 41, "data": {"actor": "Npc_oasis023", "action": "Demo_TurnAndLookToObject", "name": "Event86", "params": {"ObjectId": 1, "IsValid": true, "FaceId": 2, "UniqueName": "Thunder_Relic01", "IsWaitFinish": true, "IsConfront": true, "PosOffset": [0.0, 0.0, 0.0], "TurnPosition": [0.0, 0.0, 0.0], "TurnDirection": 0.0, "ActorName": "TwnObj_ArtifactObservationPost_A_01"}}, "node_type": "action"}, {"type": "edge", "source": 41, "target": 42, "data": {}}, {"type": "node", "id": 42, "data": {"actor": "GameROMPlayer", "action": "Demo_PlayerTurnAndLookToObject", "name": "Event87", "params": {"IsUseSlowTurn": false, "IsValid": true, "FaceId": 2, "UniqueName": "Thunder_Relic01", "IsWaitFinish": true, "ObjectId": 0, "PosOffset": [0.0, 0.0, 0.0], "TurnPosition": [0.0, 0.0, 0.0], "TurnDirection": 0.0, "ActorName": "TwnObj_ArtifactObservationPost_A_01", "IsTurnToLookAtPos": false}}, "node_type": "action"}, {"type": "edge", "source": 42, "target": 43, "data": {}}, {"type": "node", "id": 43, "data": {"actor": "EventSystemActor", "action": "Demo_WaitFrame", "name": "Event88", "params": {"IsWaitFinish": true, "Frame": 5}}, "node_type": "action"}, {"type": "edge", "source": 43, "target": 76, "data": {}}, {"type": "node", "id": 76, "data": {"actor": "GameRomCamera", "action": "Demo_MovePosFlow", "name": "Event131", "params": {"Pattern1PosX": -3756.416748046875, "Pattern1PosY": 153.57681274414062, "Pattern1PosZ": 2949.9912109375, "Pattern1AtX": -3754.776123046875, "Pattern1AtY": 153.66848754882812, "Pattern1AtZ": 2950.884033203125, "Pattern1Fovy": 14.999978065490723, "IsWaitFinish": true, "TargetActor1": -1, "ActorName1": "", "UniqueName1": "", "TargetActor2": -1, "ActorName2": "", "UniqueName2": "", "PosAppendMode": 1, "GameDataVec3fCameraPos": "", "AtAppendMode": 1, "GameDataVec3fCameraAt": "", "FovyAppendMode": 1, "StartCalcOnly": false, "Cushion": 0.0, "CollisionInterpolateSkip": true, "Accept1FrameDelay": false, "ReviseModeEnd": 1, "LatShiftRange": 0.0, "LngShiftRange": 0.0, "ActorIgnoringCollision": -1, "Count": 30.0, "MotionMode": 1}}, "node_type": "action"}, {"type": "edge", "source": 76, "target": 45, "data": {}}, {"type": "node", "id": 45, "data": {"actor": "GameRomCamera", "action": "Demo_PlayerHideOff", "name": "Event91", "params": {"IsWaitFinish": true}}, "node_type": "action"}, {"type": "edge", "source": 45, "target": 44, "data": {}}, {"type": "node", "id": 44, "data": {"actor": "EventSystemActor", "action": "Demo_WaitFrame", "name": "Event90", "params": {"IsWaitFinish": true, "Frame": 20}}, "node_type": "action"}, {"type": "edge", "source": 44, "target": 4, "data": {}}, {"type": "node", "id": 4, "data": {"actor": "Npc_oasis023", "action": "Demo_Talk", "name": "Event19", "params": {"IsWaitFinish": true, "ASName": "", "IsBecomingSpeaker": true, "MessageId": "EventFlowMsg/Npc_oasis023:Npc_oasis023_005", "IsOverWriteLabelActorName": false, "IsCloseMessageDialog": true}}, "node_type": "action"}, {"type": "edge", "source": 4, "target": 47, "data": {}}, {"type": "node", "id": 47, "data": {"actor": "EventSystemActor", "action": "Demo_WaitFrame", "name": "Event93", "params": {"Frame": 30, "IsWaitFinish": true}}, "node_type": "action"}, {"type": "edge", "source": 47, "target": 46, "data": {}}, {"type": "node", "id": 46, "data": {"actor": "GameRomCamera", "action": "Demo_ReturnSavePoint_1", "name": "Event92", "params": {"IsWaitFinish": true, "CollisionInterpolateSkip": true, "ReviseMode": 1, "Count": 0.0}}, "node_type": "action"}, {"type": "edge", "source": 46, "target": 48, "data": {}}, {"type": "node", "id": 48, "data": {"actor": "Npc_oasis023", "action": "Demo_TurnAndLookToObject", "name": "Event94", "params": {"IsValid": false, "FaceId": 2, "ObjectId": 0, "IsWaitFinish": true, "IsConfront": true, "ActorName": "", "UniqueName": "", "PosOffset": [0.0, 0.0, 0.0], "TurnPosition": [0.0, 0.0, 0.0], "TurnDirection": 0.0}}, "node_type": "action"}, {"type": "edge", "source": 48, "target": 49, "data": {}}, {"type": "node", "id": 49, "data": {"actor": "GameROMPlayer", "action": "Demo_PlayerTurnAndLookToObject", "name": "Event95", "params": {"ObjectId": 0, "IsValid": true, "FaceId": 2, "ActorName": "Npc_oasis023", "IsUseSlowTurn": false, "IsWaitFinish": true, "UniqueName": "", "PosOffset": [0.0, 0.0, 0.0], "TurnPosition": [0.0, 0.0, 0.0], "TurnDirection": 0.0, "IsTurnToLookAtPos": false}}, "node_type": "action"}, {"type": "edge", "source": 49, "target": 20, "data": {}}, {"type": "node", "id": 20, "data": {"actor": "EventSystemActor", "query": "CheckTimeType", "name": "Event46", "params": null}, "node_type": "switch"}, {"type": "edge", "source": 20, "target": 22, "data": {"value": 0}}, {"type": "node", "id": 22, "data": {"actor": "Npc_oasis023", "action": "Demo_Talk", "name": "Event48", "params": {"IsWaitFinish": true, "ASName": "", "IsBecomingSpeaker": true, "IsOverWriteLabelActorName": false, "MessageId": "EventFlowMsg/Npc_oasis023:Npc_oasis023_010", "IsCloseMessageDialog": true}}, "node_type": "action"}, {"type": "edge", "source": 22, "target": 23, "data": {}}, {"type": "edge", "source": 20, "target": 22, "data": {"value": 1}}, {"type": "edge", "source": 20, "target": 22, "data": {"value": 2}}, {"type": "edge", "source": 20, "target": 22, "data": {"value": 3}}, {"type": "edge", "source": 20, "target": 22, "data": {"value": 4}}, {"type": "edge", "source": 20, "target": 21, "data": {"value": 5}}, {"type": "node", "id": 21, "data": {"actor": "Npc_oasis023", "action": "Demo_Talk", "name": "Event47", "params": {"IsWaitFinish": true, "ASName": "", "IsBecomingSpeaker": true, "IsOverWriteLabelActorName": false, "MessageId": "EventFlowMsg/Npc_oasis023:Npc_oasis023_009", "IsCloseMessageDialog": true}}, "node_type": "action"}, {"type": "edge", "source": 21, "target": 23, "data": {}}, {"type": "edge", "source": 20, "target": 21, "data": {"value": 6}}, {"type": "edge", "source": 20, "target": 21, "data": {"value": 7}}, {"type": "edge", "source": 19, "target": 24, "data": {"value": 2}}, {"type": "node", "id": 24, "data": {"actor": "Npc_oasis023", "action": "Demo_Talk", "name": "Event50", "params": {"IsWaitFinish": true, "ASName": "", "IsBecomingSpeaker": true, "IsOverWriteLabelActorName": false, "IsCloseMessageDialog": true, "MessageId": "EventFlowMsg/Npc_oasis023:Npc_oasis023_008"}}, "node_type": "action"}, {"type": "edge", "source": 33, "target": 34, "data": {"value": 0}}, {"type": "node", "id": 34, "data": {"actor": "EventSystemActor", "query": "CheckFlag", "name": "Event78", "params": {"FlagName": "Gerudo_Ch_SnowMT_Finish"}}, "node_type": "switch"}, {"type": "edge", "source": 34, "target": 1, "data": {"value": 1}}, {"type": "node", "id": 1, "data": {"actor": "Npc_oasis023", "action": "Demo_Talk", "name": "Event3", "params": {"MessageId": "EventFlowMsg/Npc_oasis023:Npc_oasis023_001", "IsWaitFinish": true, "IsCloseMessageDialog": false, "ASName": "", "IsBecomingSpeaker": true, "IsOverWriteLabelActorName": false}}, "node_type": "action"}, {"type": "edge", "source": 34, "target": 35, "data": {"value": 0}}, {"type": "node", "id": 35, "data": {"actor": "Npc_oasis023", "action": "Demo_Talk", "name": "Event79", "params": {"IsWaitFinish": true, "IsCloseMessageDialog": false, "ASName": "", "IsBecomingSpeaker": true, "IsOverWriteLabelActorName": false, "MessageId": "EventFlowMsg/Npc_oasis023:Npc_oasis023_003"}}, "node_type": "action"}, {"type": "edge", "source": 69, "target": 32, "data": {"value": 0}}, {"type": "node", "id": 32, "data": {"actor": "RemainsElectric[Thunder_Relic01]", "action": "Demo_Join", "name": "Event76", "params": {"IsWaitFinish": false}}, "node_type": "action"}, {"type": "edge", "source": 32, "target": 33, "data": {}}, {"type": "edge", "source": 66, "target": 67, "data": {"value": 0}}, {"type": "node", "id": 67, "data": {"res_flowchart_name": "", "entry_point_name": "hello", "name": "Event117", "params": null}, "node_type": "sub_flow"}, {"type": "edge", "source": 67, "target": 56, "data": {}}, {"type": "node", "id": -1001, "data": {"name": "DemoStop"}, "node_type": "entry"}, {"type": "edge", "source": -1001, "target": 8, "data": {}}, {"type": "node", "id": 8, "data": {"actor": "EventSystemActor", "action": "Demo_WaitFrame", "name": "Event25", "params": {"IsWaitFinish": true, "Frame": 1}}, "node_type": "action"}, {"type": "edge", "source": 8, "target": 7, "data": {}}, {"type": "node", "id": 7, "data": {"res_flowchart_name": "InitTalk", "entry_point_name": "InitTalkOnEvent", "name": "Event22", "params": {"Arg_Turn": 0, "Self": "Npc_oasis023"}}, "node_type": "sub_flow"}, {"type": "edge", "source": 7, "target": 6, "data": {}}, {"type": "node", "id": 6, "data": {"actor": "Npc_oasis023", "action": "Demo_TurnAndLookToObject", "name": "Event21", "params": {"IsWaitFinish": true, "ObjectId": 0, "IsValid": true, "FaceId": 2, "ActorName": "", "UniqueName": "", "TurnPosition": [0.0, 0.0, 0.0], "TurnDirection": 0.0, "PosOffset": [0.0, 0.0, 0.0], "IsConfront": false}}, "node_type": "action"}, {"type": "edge", "source": 6, "target": 14, "data": {}}, {"type": "node", "id": 14, "data": {"name": "Event32"}, "node_type": "fork"}, {"type": "edge", "source": 14, "target": 17, "data": {}}, {"type": "node", "id": 17, "data": {"actor": "Npc_oasis023", "action": "Demo_Talk", "name": "Event38", "params": {"IsWaitFinish": true, "IsBecomingSpeaker": true, "IsOverWriteLabelActorName": false, "MessageId": "EventFlowMsg/Npc_oasis023:Npc_oasis023_001", "IsCloseMessageDialog": true, "ASName": "Guard"}}, "node_type": "action"}, {"type": "edge", "source": 17, "target": 15, "data": {"virtual": true}}, {"type": "edge", "source": 14, "target": 16, "data": {}}, {"type": "node", "id": 16, "data": {"res_flowchart_name": "SDemo_B-7", "entry_point_name": "PlayerReaction_and_Animal_CK", "name": "Event35", "params": null}, "node_type": "sub_flow"}, {"type": "edge", "source": 16, "target": 15, "data": {"virtual": true}}, {"type": "node", "id": 15, "data": {"name": "Event33"}, "node_type": "join"}, {"type": "edge", "source": 15, "target": 12, "data": {}}, {"type": "node", "id": 12, "data": {"actor": "EventSystemActor", "action": "Demo_WaitFrame", "name": "Event30", "params": {"IsWaitFinish": true, "Frame": 15}}, "node_type": "action"}, {"type": "edge", "source": 12, "target": 9, "data": {}}, {"type": "node", "id": 9, "data": {"actor": "Fader", "action": "Demo_FadeOut", "name": "Event27", "params": {"IsWaitFinish": true, "Frame": 2, "Color": 1, "DispMode": "NoLogo"}}, "node_type": "action"}, {"type": "edge", "source": 9, "target": 10, "data": {}}, {"type": "node", "id": 10, "data": {"actor": "EventSystemActor", "action": "Demo_WarpPlayer", "name": "Event28", "params": {"IsWaitFinish": true, "WarpDestMapName": "B-7", "WarpDestPosName": "WestGate_Stop"}}, "node_type": "action"}, {"type": "edge", "source": 10, "target": 18, "data": {}}, {"type": "node", "id": 18, "data": {"actor": "GameRomCamera", "action": "Demo_MovePosFlow", "name": "Event39", "params": {"Pattern1PosX": -3746.1953125, "Pattern1PosY": 151.49880981445312, "Pattern1PosZ": 2956.81201171875, "Pattern1AtX": -3750.036865234375, "Pattern1AtY": 150.59620666503906, "Pattern1AtZ": 2953.294189453125, "Pattern1Fovy": 50.00001907348633, "IsWaitFinish": true, "TargetActor1": -1, "ActorName1": "", "UniqueName1": "", "TargetActor2": -1, "ActorName2": "", "UniqueName2": "", "PosAppendMode": 1, "AtAppendMode": 1, "FovyAppendMode": 1, "StartCalcOnly": false, "MotionMode": 0, "Count": 0.0, "Cushion": 0.0, "CollisionInterpolateSkip": true, "ReviseModeEnd": 1, "LatShiftRange": 0.0, "LngShiftRange": 0.0, "ActorIgnoringCollision": -1, "Accept1FrameDelay": true, "GameDataVec3fCameraPos": "", "GameDataVec3fCameraAt": ""}}, "node_type": "action"}, {"type": "edge", "source": 18, "target": 13, "data": {}}, {"type": "node", "id": 13, "data": {"actor": "EventSystemActor", "action": "Demo_WaitFrame", "name": "Event31", "params": {"IsWaitFinish": true, "Frame": 10}}, "node_type": "action"}, {"type": "edge", "source": 13, "target": 11, "data": {}}, {"type": "node", "id": 11, "data": {"actor": "Fader", "action": "Demo_FadeIn", "name": "Event29", "params": {"IsWaitFinish": true, "Frame": 2, "Color": 1, "DispMode": "NoLogo"}}, "node_type": "action"}, {"type": "node", "id": -1002, "data": {"name": "SINJYU_CK"}, "node_type": "entry"}, {"type": "edge", "source": -1002, "target": 50, "data": {}}, {"type": "node", "id": 50, "data": {"actor": "EventSystemActor", "query": "CheckFlag", "name": "Event96", "params": {"FlagName": "IsPlayed_Demo125_0"}}, "node_type": "switch"}, {"type": "edge", "source": 50, "target": 51, "data": {"value": 1}}, {"type": "node", "id": 51, "data": {"actor": "EventSystemActor", "query": "CheckEquipArmorSeriesType", "name": "Event97", "params": {"CheckType": "GerudoCloth", "CheckHead": true, "CheckUpper": true, "CheckLower": true}}, "node_type": "switch"}, {"type": "edge", "source": 51, "target": 53, "data": {"value": 1}}, {"type": "node", "id": 53, "data": {"actor": "EventSystemActor", "query": "CheckFlag", "name": "Event99", "params": {"FlagName": "Npc_oasis023_SinjyuClear_Female"}}, "node_type": "switch"}, {"type": "edge", "source": 53, "target": 57, "data": {"value": 0}}, {"type": "node", "id": 57, "data": {"actor": "Npc_oasis023", "action": "Demo_Talk", "name": "Event105", "params": {"IsWaitFinish": true, "IsCloseMessageDialog": false, "ASName": "", "IsBecomingSpeaker": true, "IsOverWriteLabelActorName": false, "MessageId": "EventFlowMsg/Npc_oasis023:Sinjyu_Female_001"}}, "node_type": "action"}, {"type": "edge", "source": 57, "target": 54, "data": {}}, {"type": "node", "id": 54, "data": {"actor": "EventSystemActor", "action": "Demo_FlagON", "name": "Event100", "params": {"IsWaitFinish": true, "FlagName": "Npc_oasis023_SinjyuClear_Female"}}, "node_type": "action"}, {"type": "edge", "source": 54, "target": 61, "data": {}}, {"type": "node", "id": 61, "data": {"actor": "EventSystemActor", "action": "Demo_ExitEventPlayer", "name": "Event109", "params": {"IsWaitFinish": true}}, "node_type": "action"}, {"type": "edge", "source": 51, "target": 52, "data": {"value": 0}}, {"type": "node", "id": 52, "data": {"actor": "EventSystemActor", "query": "CheckFlag", "name": "Event98", "params": {"FlagName": "Npc_oasis023_SinjyuClear_Normal"}}, "node_type": "switch"}, {"type": "edge", "source": 52, "target": 58, "data": {"value": 0}}, {"type": "node", "id": 58, "data": {"actor": "Npc_oasis023", "action": "Demo_Talk", "name": "Event106", "params": {"IsWaitFinish": true, "IsCloseMessageDialog": false, "ASName": "", "IsBecomingSpeaker": true, "IsOverWriteLabelActorName": false, "MessageId": "EventFlowMsg/Npc_oasis023:Sinjyu_Normal_001"}}, "node_type": "action"}, {"type": "edge", "source": 58, "target": 55, "data": {}}, {"type": "node", "id": 55, "data": {"actor": "EventSystemActor", "action": "Demo_FlagON", "name": "Event101", "params": {"IsWaitFinish": true, "FlagName": "Npc_oasis023_SinjyuClear_Normal"}}, "node_type": "action"}, {"type": "edge", "source": 55, "target": 61, "data": {}}, {"type": "node", "id": -1003, "data": {"name": "Near"}, "node_type": "entry"}, {"type": "edge", "source": -1003, "target": 59, "data": {}}, {"type": "node", "id": 59, "data": {"actor": "EventSystemActor", "query": "CheckEquipArmorSeriesType", "name": "Event107", "params": {"CheckUpper": false, "CheckHead": true, "CheckLower": false, "CheckType": "Thunder"}}, "node_type": "switch"}, {"type": "edge", "source": 59, "target": 60, "data": {"value": 1}}, {"type": "node", "id": 60, "data": {"actor": "Npc_oasis023", "action": "Demo_TalkASync", "name": "Event108", "params": {"IsWaitFinish": true, "DispFrame": 90, "MessageId": "EventFlowMsg/Npc_oasis023:Near_Raimei_001", "IsChecked": false}}, "node_type": "action"}, {"type": "node", "id": -1004, "data": {"name": "hello"}, "node_type": "entry"}, {"type": "edge", "source": -1004, "target": 62, "data": {}}, {"type": "node", "id": 62, "data": {"actor": "EventSystemActor", "query": "CheckTimeType", "name": "Event110", "params": null}, "node_type": "switch"}, {"type": "edge", "source": 62, "target": 63, "data": {"value": 0}}, {"type": "node", "id": 63, "data": {"actor": "Npc_oasis023", "action": "Demo_Talk", "name": "Event111", "params": {"IsWaitFinish": true, "ASName": "", "IsBecomingSpeaker": true, "IsOverWriteLabelActorName": false, "IsCloseMessageDialog": true, "MessageId": "EventFlowMsg/Npc_oasis023:Npc_oasis023_013"}}, "node_type": "action"}, {"type": "edge", "source": 62, "target": 63, "data": {"value": 1}}, {"type": "edge", "source": 62, "target": 64, "data": {"value": 2}}, {"type": "node", "id": 64, "data": {"actor": "Npc_oasis023", "action": "Demo_Talk", "name": "Event112", "params": {"IsWaitFinish": true, "ASName": "", "IsBecomingSpeaker": true, "IsOverWriteLabelActorName": false, "IsCloseMessageDialog": true, "MessageId": "EventFlowMsg/Npc_oasis023:Npc_oasis023_014"}}, "node_type": "action"}, {"type": "edge", "source": 62, "target": 64, "data": {"value": 3}}, {"type": "edge", "source": 62, "target": 64, "data": {"value": 4}}, {"type": "edge", "source": 62, "target": 65, "data": {"value": 5}}, {"type": "node", "id": 65, "data": {"actor": "Npc_oasis023", "action": "Demo_Talk", "name": "Event113", "params": {"IsWaitFinish": true, "ASName": "", "IsBecomingSpeaker": true, "IsOverWriteLabelActorName": false, "IsCloseMessageDialog": true, "MessageId": "EventFlowMsg/Npc_oasis023:Npc_oasis023_015"}}, "node_type": "action"}, {"type": "edge", "source": 62, "target": 65, "data": {"value": 6}}, {"type": "edge", "source": 62, "target": 65, "data": {"value": 7}}]